[
  {
    "city": "กรุงเทพมหานคร",
    "temp": 33.83,
    "condition": "เมฆเต็มท้องฟ้า"
  },
  {
    "city": "กระบี่",
    "temp": 33.11,
    "condition": "เมฆเป็นหย่อม ๆ"
  },
  {
    "city": "กาญจนบุรี",
    "temp": 33.56,
    "condition": "เมฆเต็มท้องฟ้า"
  },
  {
    "city": "กาฬสินธุ์",
    "temp": 29.49,
    "condition": "เมฆเต็มท้องฟ้า"
  },
  {
    "city": "กำแพงเพชร",
    "temp": 30.45,
    "condition": "เมฆเต็มท้องฟ้า"
  },
  {
    "city": "ขอนแก่น",
    "temp": 31.17,
    "condition": "เมฆเป็นหย่อม ๆ"
  },
  {
    "city": "จันทบุรี",
    "temp": 33.26,
    "condition": "เมฆเป็นหย่อม ๆ"
  },
  {
    "city": "ฉะเชิงเทรา",
    "temp": 34.63,
    "condition": "เมฆเต็มท้องฟ้า"
  },
  {
    "city": "ชลบุรี",
    "temp": 33.92,
    "condition": "เมฆเต็มท้องฟ้า"
  },
  {
    "city": "ชัยนาท",
    "temp": 34.15,
    "condition": "เมฆเต็มท้องฟ้า"
  },
  {
    "city": "ชัยภูมิ",
    "temp": 31.69,
    "condition": "เมฆเต็มท้องฟ้า"
  },
  {
    "city": "ชุมพร",
    "temp": 36.52,
    "condition": "เมฆเต็มท้องฟ้า"
  },
  {
    "city": "เชียงราย",
    "temp": 26.53,
    "condition": "เมฆเป็นหย่อม ๆ"
  },
  {
    "city": "เชียงใหม่",
    "temp": 29.99,
    "condition": "เมฆเป็นหย่อม ๆ"
  },
  {
    "city": "ตรัง",
    "temp": 32.95,
    "condition": "เมฆเล็กน้อย"
  },
  {
    "city": "ตราด",
    "temp": 31.18,
    "condition": "เมฆเต็มท้องฟ้า"
  },
  {
    "city": "ตาก",
    "temp": 29.54,
    "condition": "เมฆเต็มท้องฟ้า"
  },
  {
    "city": "นครนายก",
    "temp": 34.39,
    "condition": "เมฆเต็มท้องฟ้า"
  },
  {
    "city": "นครปฐม",
    "temp": 33.3,
    "condition": "เมฆเต็มท้องฟ้า"
  },
  {
    "city": "นครพนม",
    "temp": 28.14,
    "condition": "เมฆกระจาย"
  },
  {
    "city": "นครราชสีมา",
    "temp": 34.43,
    "condition": "เมฆเต็มท้องฟ้า"
  },
  {
    "city": "นครศรีธรรมราช",
    "temp": 34.97,
    "condition": "เมฆเล็กน้อย"
  },
  {
    "city": "นครสวรรค์",
    "temp": 31.65,
    "condition": "เมฆเต็มท้องฟ้า"
  },
  {
    "city": "นนทบุรี",
    "temp": 33.98,
    "condition": "เมฆเล็กน้อย"
  },
  {
    "city": "นราธิวาส",
    "temp": 34.01,
    "condition": "เมฆเล็กน้อย"
  },
  {
    "city": "น่าน",
    "temp": 28.92,
    "condition": "เมฆเป็นหย่อม ๆ"
  },
  {
    "city": "บึงกาฬ",
    "temp": 28.12,
    "condition": "ฝนปานกลาง"
  },
  {
    "city": "บุรีรัมย์",
    "temp": 31.71,
    "condition": "ฝนเบา ๆ"
  },
  {
    "city": "ปทุมธานี",
    "temp": 33.99,
    "condition": "เมฆเล็กน้อย"
  },
  {
    "city": "ประจวบคีรีขันธ์",
    "temp": 34.06,
    "condition": "เมฆเต็มท้องฟ้า"
  },
  {
    "city": "ปราจีนบุรี",
    "temp": 34.21,
    "condition": "เมฆเต็มท้องฟ้า"
  },
  {
    "city": "ปัตตานี",
    "temp": 32.78,
    "condition": "เมฆเป็นหย่อม ๆ"
  },
  {
    "city": "พระนครศรีอยุธยา",
    "temp": 34.16,
    "condition": "เมฆเต็มท้องฟ้า"
  },
  {
    "city": "พังงา",
    "temp": 32.38,
    "condition": "เมฆกระจาย"
  },
  {
    "city": "พัทลุง",
    "temp": 33.83,
    "condition": "เมฆเป็นหย่อม ๆ"
  },
  {
    "city": "พิจิตร",
    "temp": 32.31,
    "condition": "เมฆเต็มท้องฟ้า"
  },
  {
    "city": "พิษณุโลก",
    "temp": 29.97,
    "condition": "ท้องฟ้าแจ่มใส"
  },
  {
    "city": "เพชรบุรี",
    "temp": 34.09,
    "condition": "เมฆเต็มท้องฟ้า"
  },
  {
    "city": "เพชรบูรณ์",
    "temp": 29.12,
    "condition": "เมฆเต็มท้องฟ้า"
  },
  {
    "city": "แพร่",
    "temp": 27.81,
    "condition": "เมฆเล็กน้อย"
  },
  {
    "city": "ภูเก็ต",
    "temp": 32.12,
    "condition": "เมฆเล็กน้อย"
  },
  {
    "city": "มหาสารคาม",
    "temp": 30.48,
    "condition": "เมฆเต็มท้องฟ้า"
  },
  {
    "city": "มุกดาหาร",
    "temp": 27.02,
    "condition": "ฝนปรอย"
  },
  {
    "city": "แม่ฮ่องสอน",
    "temp": 28.08,
    "condition": "เมฆเป็นหย่อม ๆ"
  },
  {
    "city": "ยโสธร",
    "temp": 31.2,
    "condition": "เมฆเต็มท้องฟ้า"
  },
  {
    "city": "ยะลา",
    "temp": 37.27,
    "condition": "เมฆเป็นหย่อม ๆ"
  },
  {
    "city": "ร้อยเอ็ด",
    "temp": 30.9,
    "condition": "เมฆกระจาย"
  },
  {
    "city": "ระนอง",
    "temp": 31.96,
    "condition": "เมฆเป็นหย่อม ๆ"
  },
  {
    "city": "ระยอง",
    "temp": 33.33,
    "condition": "เมฆเป็นหย่อม ๆ"
  },
  {
    "city": "ราชบุรี",
    "temp": 35,
    "condition": "เมฆเต็มท้องฟ้า"
  },
  {
    "city": "ลพบุรี",
    "temp": 33.26,
    "condition": "เมฆเต็มท้องฟ้า"
  },
  {
    "city": "ลำปาง",
    "temp": 29.04,
    "condition": "เมฆเป็นหย่อม ๆ"
  },
  {
    "city": "ลำพูน",
    "temp": 30.1,
    "condition": "เมฆเต็มท้องฟ้า"
  },
  {
    "city": "เลย",
    "temp": 29.07,
    "condition": "เมฆเป็นหย่อม ๆ"
  },
  {
    "city": "ศรีสะเกษ",
    "temp": 32.58,
    "condition": "เมฆเต็มท้องฟ้า"
  },
  {
    "city": "สกลนคร",
    "temp": 29.97,
    "condition": "เมฆเป็นหย่อม ๆ"
  },
  {
    "city": "สงขลา",
    "temp": 33.95,
    "condition": "เมฆเต็มท้องฟ้า"
  },
  {
    "city": "สตูล",
    "temp": 33.08,
    "condition": "เมฆเป็นหย่อม ๆ"
  },
  {
    "city": "สมุทรปราการ",
    "temp": 33,
    "condition": "เมฆเล็กน้อย"
  },
  {
    "city": "สมุทรสงคราม",
    "temp": 34.44,
    "condition": "เมฆเต็มท้องฟ้า"
  },
  {
    "city": "สมุทรสาคร",
    "temp": 33.31,
    "condition": "เมฆเต็มท้องฟ้า"
  },
  {
    "city": "สระแก้ว",
    "temp": 33.79,
    "condition": "เมฆเต็มท้องฟ้า"
  },
  {
    "city": "สระบุรี",
    "temp": 34.49,
    "condition": "เมฆเต็มท้องฟ้า"
  },
  {
    "city": "สิงห์บุรี",
    "temp": 34.99,
    "condition": "เมฆเต็มท้องฟ้า"
  },
  {
    "city": "สุโขทัย",
    "temp": 30.02,
    "condition": "เมฆเต็มท้องฟ้า"
  },
  {
    "city": "สุพรรณบุรี",
    "temp": 34.15,
    "condition": "เมฆเต็มท้องฟ้า"
  },
  {
    "city": "สุราษฎร์ธานี",
    "temp": 36.1,
    "condition": "เมฆเล็กน้อย"
  },
  {
    "city": "สุรินทร์",
    "temp": 32.73,
    "condition": "เมฆเต็มท้องฟ้า"
  },
  {
    "city": "หนองคาย",
    "temp": 30.01,
    "condition": "เมฆเต็มท้องฟ้า"
  },
  {
    "city": "หนองบัวลำภู",
    "temp": 28.61,
    "condition": "เมฆเต็มท้องฟ้า"
  },
  {
    "city": "อ่างทอง",
    "temp": 33.3,
    "condition": "เมฆเต็มท้องฟ้า"
  },
  {
    "city": "อำนาจเจริญ",
    "temp": 29.38,
    "condition": "ฝนเบา ๆ"
  },
  {
    "city": "อุดรธานี",
    "temp": 29.95,
    "condition": "เมฆกระจาย"
  },
  {
    "city": "อุตรดิตถ์",
    "temp": 29.91,
    "condition": "เมฆเต็มท้องฟ้า"
  },
  {
    "city": "อุทัยธานี",
    "temp": 33.76,
    "condition": "เมฆเต็มท้องฟ้า"
  },
  {
    "city": "อุบลราชธานี",
    "temp": 29.38,
    "condition": "เมฆเต็มท้องฟ้า"
  }
]