[
  {
    "city": "กรุงเทพมหานคร",
    "temp": 32.74,
    "condition": "เมฆเต็มท้องฟ้า"
  },
  {
    "city": "กระบี่",
    "temp": 30.11,
    "condition": "ฝนแบบแรง"
  },
  {
    "city": "กาญจนบุรี",
    "temp": 29.79,
    "condition": "เมฆเป็นหย่อม ๆ"
  },
  {
    "city": "กาฬสินธุ์",
    "temp": 32.99,
    "condition": "เมฆเป็นหย่อม ๆ"
  },
  {
    "city": "กำแพงเพชร",
    "temp": 30.53,
    "condition": "เมฆเป็นหย่อม ๆ"
  },
  {
    "city": "ขอนแก่น",
    "temp": 30.17,
    "condition": "เมฆเล็กน้อย"
  },
  {
    "city": "จันทบุรี",
    "temp": 28.58,
    "condition": "เมฆเป็นหย่อม ๆ"
  },
  {
    "city": "ฉะเชิงเทรา",
    "temp": 30.98,
    "condition": "เมฆเต็มท้องฟ้า"
  },
  {
    "city": "ชลบุรี",
    "temp": 33.53,
    "condition": "เมฆเป็นหย่อม ๆ"
  },
  {
    "city": "ชัยนาท",
    "temp": 33.67,
    "condition": "เมฆกระจาย"
  },
  {
    "city": "ชัยภูมิ",
    "temp": 30.22,
    "condition": "ฝนเบา ๆ"
  },
  {
    "city": "ชุมพร",
    "temp": 26.65,
    "condition": "เมฆกระจาย"
  },
  {
    "city": "เชียงราย",
    "temp": 27.46,
    "condition": "เมฆเล็กน้อย"
  },
  {
    "city": "เชียงใหม่",
    "temp": 26.97,
    "condition": "เมฆเป็นหย่อม ๆ"
  },
  {
    "city": "ตรัง",
    "temp": 25.95,
    "condition": "เมฆเล็กน้อย"
  },
  {
    "city": "ตราด",
    "temp": 29.18,
    "condition": "ฝนเบา ๆ"
  },
  {
    "city": "ตาก",
    "temp": 28.68,
    "condition": "เมฆเป็นหย่อม ๆ"
  },
  {
    "city": "นครนายก",
    "temp": 32.27,
    "condition": "เมฆเต็มท้องฟ้า"
  },
  {
    "city": "นครปฐม",
    "temp": 31.66,
    "condition": "เมฆเป็นหย่อม ๆ"
  },
  {
    "city": "นครพนม",
    "temp": 32.14,
    "condition": "เมฆเล็กน้อย"
  },
  {
    "city": "นครราชสีมา",
    "temp": 24.26,
    "condition": "เมฆเป็นหย่อม ๆ"
  },
  {
    "city": "นครศรีธรรมราช",
    "temp": 27.97,
    "condition": "เมฆเป็นหย่อม ๆ"
  },
  {
    "city": "นครสวรรค์",
    "temp": 32.37,
    "condition": "เมฆเป็นหย่อม ๆ"
  },
  {
    "city": "นนทบุรี",
    "temp": 33.6,
    "condition": "ฝนเบา ๆ"
  },
  {
    "city": "นราธิวาส",
    "temp": 30.01,
    "condition": "เมฆเล็กน้อย"
  },
  {
    "city": "น่าน",
    "temp": 31.92,
    "condition": "เมฆเล็กน้อย"
  },
  {
    "city": "บึงกาฬ",
    "temp": 31.04,
    "condition": "เมฆกระจาย"
  },
  {
    "city": "บุรีรัมย์",
    "temp": 28.53,
    "condition": "เมฆเต็มท้องฟ้า"
  },
  {
    "city": "ปทุมธานี",
    "temp": 35.48,
    "condition": "ฝนเบา ๆ"
  },
  {
    "city": "ประจวบคีรีขันธ์",
    "temp": 28.12,
    "condition": "เมฆเป็นหย่อม ๆ"
  },
  {
    "city": "ปราจีนบุรี",
    "temp": 31.04,
    "condition": "เมฆเป็นหย่อม ๆ"
  },
  {
    "city": "ปัตตานี",
    "temp": 26.12,
    "condition": "เมฆเป็นหย่อม ๆ"
  },
  {
    "city": "พระนครศรีอยุธยา",
    "temp": 33.3,
    "condition": "เมฆเป็นหย่อม ๆ"
  },
  {
    "city": "พังงา",
    "temp": 26.4,
    "condition": "เมฆเป็นหย่อม ๆ"
  },
  {
    "city": "พัทลุง",
    "temp": 28.06,
    "condition": "เมฆเต็มท้องฟ้า"
  },
  {
    "city": "พิจิตร",
    "temp": 32.88,
    "condition": "เมฆเป็นหย่อม ๆ"
  },
  {
    "city": "พิษณุโลก",
    "temp": 32.41,
    "condition": "เมฆเล็กน้อย"
  },
  {
    "city": "เพชรบุรี",
    "temp": 30.2,
    "condition": "เมฆเต็มท้องฟ้า"
  },
  {
    "city": "เพชรบูรณ์",
    "temp": 28.12,
    "condition": "เมฆกระจาย"
  },
  {
    "city": "แพร่",
    "temp": 29.2,
    "condition": "เมฆเป็นหย่อม ๆ"
  },
  {
    "city": "ภูเก็ต",
    "temp": 29.12,
    "condition": "ฝนเบา ๆ"
  },
  {
    "city": "มหาสารคาม",
    "temp": 31.62,
    "condition": "เมฆเต็มท้องฟ้า"
  },
  {
    "city": "มุกดาหาร",
    "temp": 31.49,
    "condition": "ฝนปานกลาง"
  },
  {
    "city": "แม่ฮ่องสอน",
    "temp": 31.08,
    "condition": "เมฆกระจาย"
  },
  {
    "city": "ยโสธร",
    "temp": 30.74,
    "condition": "เมฆเต็มท้องฟ้า"
  },
  {
    "city": "ยะลา",
    "temp": 27.71,
    "condition": "เมฆกระจาย"
  },
  {
    "city": "ร้อยเอ็ด",
    "temp": 32.9,
    "condition": "เมฆกระจาย"
  },
  {
    "city": "ระนอง",
    "temp": 29.96,
    "condition": "เมฆเป็นหย่อม ๆ"
  },
  {
    "city": "ระยอง",
    "temp": 30,
    "condition": "เมฆเป็นหย่อม ๆ"
  },
  {
    "city": "ราชบุรี",
    "temp": 30.77,
    "condition": "เมฆเต็มท้องฟ้า"
  },
  {
    "city": "ลพบุรี",
    "temp": 36.04,
    "condition": "เมฆเป็นหย่อม ๆ"
  },
  {
    "city": "ลำปาง",
    "temp": 29.04,
    "condition": "เมฆเป็นหย่อม ๆ"
  },
  {
    "city": "ลำพูน",
    "temp": 27.1,
    "condition": "เมฆเป็นหย่อม ๆ"
  },
  {
    "city": "เลย",
    "temp": 26.07,
    "condition": "เมฆเป็นหย่อม ๆ"
  },
  {
    "city": "ศรีสะเกษ",
    "temp": 30.34,
    "condition": "เมฆเป็นหย่อม ๆ"
  },
  {
    "city": "สกลนคร",
    "temp": 31.97,
    "condition": "ท้องฟ้าแจ่มใส"
  },
  {
    "city": "สงขลา",
    "temp": 31.11,
    "condition": "เมฆเป็นหย่อม ๆ"
  },
  {
    "city": "สตูล",
    "temp": 27.66,
    "condition": "ฝนปานกลาง"
  },
  {
    "city": "สมุทรปราการ",
    "temp": 32.81,
    "condition": "เมฆเต็มท้องฟ้า"
  },
  {
    "city": "สมุทรสงคราม",
    "temp": 30.74,
    "condition": "เมฆเต็มท้องฟ้า"
  },
  {
    "city": "สมุทรสาคร",
    "temp": 31.31,
    "condition": "เมฆเต็มท้องฟ้า"
  },
  {
    "city": "สระแก้ว",
    "temp": 30.24,
    "condition": "ฝนเบา ๆ"
  },
  {
    "city": "สระบุรี",
    "temp": 33.27,
    "condition": "เมฆเป็นหย่อม ๆ"
  },
  {
    "city": "สิงห์บุรี",
    "temp": 36.06,
    "condition": "เมฆกระจาย"
  },
  {
    "city": "สุโขทัย",
    "temp": 34.02,
    "condition": "เมฆเป็นหย่อม ๆ"
  },
  {
    "city": "สุพรรณบุรี",
    "temp": 33.15,
    "condition": "เมฆกระจาย"
  },
  {
    "city": "สุราษฎร์ธานี",
    "temp": 27.93,
    "condition": "เมฆเป็นหย่อม ๆ"
  },
  {
    "city": "สุรินทร์",
    "temp": 28.92,
    "condition": "เมฆเต็มท้องฟ้า"
  },
  {
    "city": "หนองคาย",
    "temp": 31.84,
    "condition": "เมฆกระจาย"
  },
  {
    "city": "หนองบัวลำภู",
    "temp": 31.98,
    "condition": "เมฆกระจาย"
  },
  {
    "city": "อ่างทอง",
    "temp": 36.08,
    "condition": "เมฆเป็นหย่อม ๆ"
  },
  {
    "city": "อำนาจเจริญ",
    "temp": 30.72,
    "condition": "เมฆเต็มท้องฟ้า"
  },
  {
    "city": "อุดรธานี",
    "temp": 28.95,
    "condition": "พายุฟ้าคะนอง"
  },
  {
    "city": "อุตรดิตถ์",
    "temp": 32.77,
    "condition": "เมฆกระจาย"
  },
  {
    "city": "อุทัยธานี",
    "temp": 32.99,
    "condition": "ฝนเบา ๆ"
  },
  {
    "city": "อุบลราชธานี",
    "temp": 31.16,
    "condition": "เมฆเต็มท้องฟ้า"
  }
]