[
  {
    "city": "กรุงเทพมหานคร",
    "temp": 30.84,
    "condition": "เมฆเต็มท้องฟ้า"
  },
  {
    "city": "กระบี่",
    "temp": 28.11,
    "condition": "เมฆเล็กน้อย"
  },
  {
    "city": "กาญจนบุรี",
    "temp": 30.1,
    "condition": "เมฆกระจาย"
  },
  {
    "city": "กาฬสินธุ์",
    "temp": 32.99,
    "condition": "เมฆเต็มท้องฟ้า"
  },
  {
    "city": "กำแพงเพชร",
    "temp": 29.17,
    "condition": "เมฆเล็กน้อย"
  },
  {
    "city": "ขอนแก่น",
    "temp": 30.17,
    "condition": "เมฆเล็กน้อย"
  },
  {
    "city": "จันทบุรี",
    "temp": 27.7,
    "condition": "เมฆเล็กน้อย"
  },
  {
    "city": "ฉะเชิงเทรา",
    "temp": 30.08,
    "condition": "เมฆเป็นหย่อม ๆ"
  },
  {
    "city": "ชลบุรี",
    "temp": 31.87,
    "condition": "เมฆเป็นหย่อม ๆ"
  },
  {
    "city": "ชัยนาท",
    "temp": 29.17,
    "condition": "เมฆเต็มท้องฟ้า"
  },
  {
    "city": "ชัยภูมิ",
    "temp": 28.34,
    "condition": "เมฆเป็นหย่อม ๆ"
  },
  {
    "city": "ชุมพร",
    "temp": 28.87,
    "condition": "เมฆเป็นหย่อม ๆ"
  },
  {
    "city": "เชียงราย",
    "temp": 26.35,
    "condition": "เมฆเล็กน้อย"
  },
  {
    "city": "เชียงใหม่",
    "temp": 27.97,
    "condition": "เมฆเป็นหย่อม ๆ"
  },
  {
    "city": "ตรัง",
    "temp": 26.95,
    "condition": "เมฆเล็กน้อย"
  },
  {
    "city": "ตราด",
    "temp": 27.41,
    "condition": "เมฆเล็กน้อย"
  },
  {
    "city": "ตาก",
    "temp": 28.56,
    "condition": "เมฆกระจาย"
  },
  {
    "city": "นครนายก",
    "temp": 28.86,
    "condition": "เมฆเต็มท้องฟ้า"
  },
  {
    "city": "นครปฐม",
    "temp": 28.86,
    "condition": "เมฆเต็มท้องฟ้า"
  },
  {
    "city": "นครพนม",
    "temp": 30.14,
    "condition": "ท้องฟ้าแจ่มใส"
  },
  {
    "city": "นครราชสีมา",
    "temp": 28.26,
    "condition": "เมฆเต็มท้องฟ้า"
  },
  {
    "city": "นครศรีธรรมราช",
    "temp": 25.97,
    "condition": "เมฆกระจาย"
  },
  {
    "city": "นครสวรรค์",
    "temp": 28.66,
    "condition": "เมฆเป็นหย่อม ๆ"
  },
  {
    "city": "นนทบุรี",
    "temp": 31.44,
    "condition": "เมฆเล็กน้อย"
  },
  {
    "city": "นราธิวาส",
    "temp": 29.08,
    "condition": "เมฆเป็นหย่อม ๆ"
  },
  {
    "city": "น่าน",
    "temp": 25.92,
    "condition": "เมฆเล็กน้อย"
  },
  {
    "city": "บึงกาฬ",
    "temp": 29.27,
    "condition": "เมฆเป็นหย่อม ๆ"
  },
  {
    "city": "บุรีรัมย์",
    "temp": 28.49,
    "condition": "เมฆเป็นหย่อม ๆ"
  },
  {
    "city": "ปทุมธานี",
    "temp": 31.03,
    "condition": "เมฆเล็กน้อย"
  },
  {
    "city": "ประจวบคีรีขันธ์",
    "temp": 27.44,
    "condition": "เมฆกระจาย"
  },
  {
    "city": "ปราจีนบุรี",
    "temp": 29.14,
    "condition": "เมฆเป็นหย่อม ๆ"
  },
  {
    "city": "ปัตตานี",
    "temp": 27.23,
    "condition": "เมฆเต็มท้องฟ้า"
  },
  {
    "city": "พระนครศรีอยุธยา",
    "temp": 32.75,
    "condition": "เมฆเต็มท้องฟ้า"
  },
  {
    "city": "พังงา",
    "temp": 25.69,
    "condition": "ฝนเบา ๆ"
  },
  {
    "city": "พัทลุง",
    "temp": 29.31,
    "condition": "ฝนปานกลาง"
  },
  {
    "city": "พิจิตร",
    "temp": 30.79,
    "condition": "ท้องฟ้าแจ่มใส"
  },
  {
    "city": "พิษณุโลก",
    "temp": 24.97,
    "condition": "เมฆเป็นหย่อม ๆ"
  },
  {
    "city": "เพชรบุรี",
    "temp": 30.12,
    "condition": "เมฆเล็กน้อย"
  },
  {
    "city": "เพชรบูรณ์",
    "temp": 28.26,
    "condition": "เมฆเล็กน้อย"
  },
  {
    "city": "แพร่",
    "temp": 29.08,
    "condition": "เมฆเต็มท้องฟ้า"
  },
  {
    "city": "ภูเก็ต",
    "temp": 28.12,
    "condition": "เมฆเล็กน้อย"
  },
  {
    "city": "มหาสารคาม",
    "temp": 30.51,
    "condition": "เมฆเต็มท้องฟ้า"
  },
  {
    "city": "มุกดาหาร",
    "temp": 29.33,
    "condition": "ฝนเบา ๆ"
  },
  {
    "city": "แม่ฮ่องสอน",
    "temp": 28.47,
    "condition": "เมฆกระจาย"
  },
  {
    "city": "ยโสธร",
    "temp": 29.47,
    "condition": "เมฆเต็มท้องฟ้า"
  },
  {
    "city": "ยะลา",
    "temp": 28.36,
    "condition": "เมฆเต็มท้องฟ้า"
  },
  {
    "city": "ร้อยเอ็ด",
    "temp": 28.9,
    "condition": "เมฆเล็กน้อย"
  },
  {
    "city": "ระนอง",
    "temp": 27.66,
    "condition": "เมฆเต็มท้องฟ้า"
  },
  {
    "city": "ระยอง",
    "temp": 28.33,
    "condition": "เมฆกระจาย"
  },
  {
    "city": "ราชบุรี",
    "temp": 31.65,
    "condition": "เมฆเป็นหย่อม ๆ"
  },
  {
    "city": "ลพบุรี",
    "temp": 31.06,
    "condition": "เมฆเต็มท้องฟ้า"
  },
  {
    "city": "ลำปาง",
    "temp": 30.04,
    "condition": "เมฆเป็นหย่อม ๆ"
  },
  {
    "city": "ลำพูน",
    "temp": 28.1,
    "condition": "เมฆกระจาย"
  },
  {
    "city": "เลย",
    "temp": 28.07,
    "condition": "เมฆเล็กน้อย"
  },
  {
    "city": "ศรีสะเกษ",
    "temp": 29.46,
    "condition": "เมฆเต็มท้องฟ้า"
  },
  {
    "city": "สกลนคร",
    "temp": 30.15,
    "condition": "เมฆเป็นหย่อม ๆ"
  },
  {
    "city": "สงขลา",
    "temp": 30.89,
    "condition": "เมฆเต็มท้องฟ้า"
  },
  {
    "city": "สตูล",
    "temp": 28.73,
    "condition": "เมฆเต็มท้องฟ้า"
  },
  {
    "city": "สมุทรปราการ",
    "temp": 30,
    "condition": "เมฆเล็กน้อย"
  },
  {
    "city": "สมุทรสงคราม",
    "temp": 31.67,
    "condition": "เมฆกระจาย"
  },
  {
    "city": "สมุทรสาคร",
    "temp": 28.87,
    "condition": "เมฆกระจาย"
  },
  {
    "city": "สระแก้ว",
    "temp": 28.7,
    "condition": "เมฆเต็มท้องฟ้า"
  },
  {
    "city": "สระบุรี",
    "temp": 31.05,
    "condition": "เมฆเต็มท้องฟ้า"
  },
  {
    "city": "สิงห์บุรี",
    "temp": 30.17,
    "condition": "เมฆเต็มท้องฟ้า"
  },
  {
    "city": "สุโขทัย",
    "temp": 30.34,
    "condition": "เมฆเป็นหย่อม ๆ"
  },
  {
    "city": "สุพรรณบุรี",
    "temp": 30.57,
    "condition": "เมฆเป็นหย่อม ๆ"
  },
  {
    "city": "สุราษฎร์ธานี",
    "temp": 27.79,
    "condition": "เมฆเต็มท้องฟ้า"
  },
  {
    "city": "สุรินทร์",
    "temp": 28.85,
    "condition": "เมฆเต็มท้องฟ้า"
  },
  {
    "city": "หนองคาย",
    "temp": 28.01,
    "condition": "เมฆเล็กน้อย"
  },
  {
    "city": "หนองบัวลำภู",
    "temp": 29.57,
    "condition": "ฝนปานกลาง"
  },
  {
    "city": "อ่างทอง",
    "temp": 30.78,
    "condition": "เมฆเป็นหย่อม ๆ"
  },
  {
    "city": "อำนาจเจริญ",
    "temp": 28.72,
    "condition": "เมฆเต็มท้องฟ้า"
  },
  {
    "city": "อุดรธานี",
    "temp": 26.95,
    "condition": "เมฆกระจาย"
  },
  {
    "city": "อุตรดิตถ์",
    "temp": 27.77,
    "condition": "เมฆเป็นหย่อม ๆ"
  },
  {
    "city": "อุทัยธานี",
    "temp": 28.82,
    "condition": "เมฆเต็มท้องฟ้า"
  },
  {
    "city": "อุบลราชธานี",
    "temp": 27.46,
    "condition": "เมฆเต็มท้องฟ้า"
  }
]