[
  {
    "city": "กรุงเทพมหานคร",
    "temp": 30.86,
    "condition": "เมฆเต็มท้องฟ้า"
  },
  {
    "city": "กระบี่",
    "temp": 28.11,
    "condition": "เมฆเล็กน้อย"
  },
  {
    "city": "กาญจนบุรี",
    "temp": 30.44,
    "condition": "เมฆเต็มท้องฟ้า"
  },
  {
    "city": "กาฬสินธุ์",
    "temp": 29.09,
    "condition": "เมฆเป็นหย่อม ๆ"
  },
  {
    "city": "กำแพงเพชร",
    "temp": 30.47,
    "condition": "เมฆเต็มท้องฟ้า"
  },
  {
    "city": "ขอนแก่น",
    "temp": 30.17,
    "condition": "ท้องฟ้าแจ่มใส"
  },
  {
    "city": "จันทบุรี",
    "temp": 27.84,
    "condition": "เมฆเป็นหย่อม ๆ"
  },
  {
    "city": "ฉะเชิงเทรา",
    "temp": 30.32,
    "condition": "เมฆเต็มท้องฟ้า"
  },
  {
    "city": "ชลบุรี",
    "temp": 26.14,
    "condition": "เมฆเต็มท้องฟ้า"
  },
  {
    "city": "ชัยนาท",
    "temp": 31.38,
    "condition": "เมฆเป็นหย่อม ๆ"
  },
  {
    "city": "ชัยภูมิ",
    "temp": 30.22,
    "condition": "เมฆเป็นหย่อม ๆ"
  },
  {
    "city": "ชุมพร",
    "temp": 28.87,
    "condition": "เมฆเต็มท้องฟ้า"
  },
  {
    "city": "เชียงราย",
    "temp": 25.8,
    "condition": "เมฆเป็นหย่อม ๆ"
  },
  {
    "city": "เชียงใหม่",
    "temp": 28.78,
    "condition": "เมฆเป็นหย่อม ๆ"
  },
  {
    "city": "ตรัง",
    "temp": 26.51,
    "condition": "เมฆเต็มท้องฟ้า"
  },
  {
    "city": "ตราด",
    "temp": 26.97,
    "condition": "เมฆเต็มท้องฟ้า"
  },
  {
    "city": "ตาก",
    "temp": 29.13,
    "condition": "เมฆเต็มท้องฟ้า"
  },
  {
    "city": "นครนายก",
    "temp": 30.97,
    "condition": "เมฆเต็มท้องฟ้า"
  },
  {
    "city": "นครปฐม",
    "temp": 29.41,
    "condition": "เมฆเป็นหย่อม ๆ"
  },
  {
    "city": "นครพนม",
    "temp": 27.14,
    "condition": "ฝนเบา ๆ"
  },
  {
    "city": "นครราชสีมา",
    "temp": 28.26,
    "condition": "เมฆกระจาย"
  },
  {
    "city": "นครศรีธรรมราช",
    "temp": 24.97,
    "condition": "เมฆเล็กน้อย"
  },
  {
    "city": "นครสวรรค์",
    "temp": 31.17,
    "condition": "เมฆเป็นหย่อม ๆ"
  },
  {
    "city": "นนทบุรี",
    "temp": 30.6,
    "condition": "เมฆเล็กน้อย"
  },
  {
    "city": "นราธิวาส",
    "temp": 29.3,
    "condition": "เมฆกระจาย"
  },
  {
    "city": "น่าน",
    "temp": 25.65,
    "condition": "เมฆกระจาย"
  },
  {
    "city": "บึงกาฬ",
    "temp": 29.01,
    "condition": "เมฆเต็มท้องฟ้า"
  },
  {
    "city": "บุรีรัมย์",
    "temp": 29.44,
    "condition": "เมฆเต็มท้องฟ้า"
  },
  {
    "city": "ปทุมธานี",
    "temp": 30.26,
    "condition": "เมฆเล็กน้อย"
  },
  {
    "city": "ประจวบคีรีขันธ์",
    "temp": 27.44,
    "condition": "เมฆเป็นหย่อม ๆ"
  },
  {
    "city": "ปราจีนบุรี",
    "temp": 30.04,
    "condition": "เมฆเต็มท้องฟ้า"
  },
  {
    "city": "ปัตตานี",
    "temp": 26.68,
    "condition": "เมฆกระจาย"
  },
  {
    "city": "พระนครศรีอยุธยา",
    "temp": 31.42,
    "condition": "เมฆเต็มท้องฟ้า"
  },
  {
    "city": "พังงา",
    "temp": 26.61,
    "condition": "เมฆเต็มท้องฟ้า"
  },
  {
    "city": "พัทลุง",
    "temp": 27.83,
    "condition": "เมฆเต็มท้องฟ้า"
  },
  {
    "city": "พิจิตร",
    "temp": 31.47,
    "condition": "เมฆเป็นหย่อม ๆ"
  },
  {
    "city": "พิษณุโลก",
    "temp": 29.99,
    "condition": "เมฆเต็มท้องฟ้า"
  },
  {
    "city": "เพชรบุรี",
    "temp": 30.23,
    "condition": "เมฆเต็มท้องฟ้า"
  },
  {
    "city": "เพชรบูรณ์",
    "temp": 29.52,
    "condition": "เมฆกระจาย"
  },
  {
    "city": "แพร่",
    "temp": 27.88,
    "condition": "เมฆเต็มท้องฟ้า"
  },
  {
    "city": "ภูเก็ต",
    "temp": 27.12,
    "condition": "เมฆเล็กน้อย"
  },
  {
    "city": "มหาสารคาม",
    "temp": 29.24,
    "condition": "เมฆเป็นหย่อม ๆ"
  },
  {
    "city": "มุกดาหาร",
    "temp": 26.24,
    "condition": "เมฆเป็นหย่อม ๆ"
  },
  {
    "city": "แม่ฮ่องสอน",
    "temp": 26.13,
    "condition": "เมฆเป็นหย่อม ๆ"
  },
  {
    "city": "ยโสธร",
    "temp": 28.42,
    "condition": "เมฆเป็นหย่อม ๆ"
  },
  {
    "city": "ยะลา",
    "temp": 28.38,
    "condition": "เมฆเป็นหย่อม ๆ"
  },
  {
    "city": "ร้อยเอ็ด",
    "temp": 29.9,
    "condition": "เมฆเล็กน้อย"
  },
  {
    "city": "ระนอง",
    "temp": 27.85,
    "condition": "ฝนปานกลาง"
  },
  {
    "city": "ระยอง",
    "temp": 29.05,
    "condition": "เมฆเป็นหย่อม ๆ"
  },
  {
    "city": "ราชบุรี",
    "temp": 30.66,
    "condition": "เมฆเป็นหย่อม ๆ"
  },
  {
    "city": "ลพบุรี",
    "temp": 31.06,
    "condition": "เมฆเต็มท้องฟ้า"
  },
  {
    "city": "ลำปาง",
    "temp": 28.54,
    "condition": "เมฆเป็นหย่อม ๆ"
  },
  {
    "city": "ลำพูน",
    "temp": 29.1,
    "condition": "เมฆกระจาย"
  },
  {
    "city": "เลย",
    "temp": 28.73,
    "condition": "เมฆเต็มท้องฟ้า"
  },
  {
    "city": "ศรีสะเกษ",
    "temp": 28.54,
    "condition": "เมฆเต็มท้องฟ้า"
  },
  {
    "city": "สกลนคร",
    "temp": 27.86,
    "condition": "เมฆเต็มท้องฟ้า"
  },
  {
    "city": "สงขลา",
    "temp": 28.74,
    "condition": "เมฆเป็นหย่อม ๆ"
  },
  {
    "city": "สตูล",
    "temp": 28.57,
    "condition": "เมฆเป็นหย่อม ๆ"
  },
  {
    "city": "สมุทรปราการ",
    "temp": 30,
    "condition": "เมฆเล็กน้อย"
  },
  {
    "city": "สมุทรสงคราม",
    "temp": 30.64,
    "condition": "เมฆเต็มท้องฟ้า"
  },
  {
    "city": "สมุทรสาคร",
    "temp": 29.42,
    "condition": "เมฆเต็มท้องฟ้า"
  },
  {
    "city": "สระแก้ว",
    "temp": 28.78,
    "condition": "เมฆเต็มท้องฟ้า"
  },
  {
    "city": "สระบุรี",
    "temp": 31.05,
    "condition": "เมฆเต็มท้องฟ้า"
  },
  {
    "city": "สิงห์บุรี",
    "temp": 31.63,
    "condition": "ฝนเบา ๆ"
  },
  {
    "city": "สุโขทัย",
    "temp": 31.24,
    "condition": "เมฆเต็มท้องฟ้า"
  },
  {
    "city": "สุพรรณบุรี",
    "temp": 31.39,
    "condition": "เมฆเต็มท้องฟ้า"
  },
  {
    "city": "สุราษฎร์ธานี",
    "temp": 27.79,
    "condition": "เมฆเต็มท้องฟ้า"
  },
  {
    "city": "สุรินทร์",
    "temp": 28.81,
    "condition": "เมฆเต็มท้องฟ้า"
  },
  {
    "city": "หนองคาย",
    "temp": 29.01,
    "condition": "เมฆเต็มท้องฟ้า"
  },
  {
    "city": "หนองบัวลำภู",
    "temp": 30.6,
    "condition": "เมฆเต็มท้องฟ้า"
  },
  {
    "city": "อ่างทอง",
    "temp": 31.5,
    "condition": "เมฆเต็มท้องฟ้า"
  },
  {
    "city": "อำนาจเจริญ",
    "temp": 28.07,
    "condition": "เมฆเป็นหย่อม ๆ"
  },
  {
    "city": "อุดรธานี",
    "temp": 29.95,
    "condition": "ท้องฟ้าแจ่มใส"
  },
  {
    "city": "อุตรดิตถ์",
    "temp": 28.09,
    "condition": "เมฆเต็มท้องฟ้า"
  },
  {
    "city": "อุทัยธานี",
    "temp": 31.19,
    "condition": "เมฆเป็นหย่อม ๆ"
  },
  {
    "city": "อุบลราชธานี",
    "temp": 28.5,
    "condition": "เมฆเป็นหย่อม ๆ"
  }
]