[
  {
    "city": "กรุงเทพมหานคร",
    "temp": 32.63,
    "condition": "เมฆเต็มท้องฟ้า"
  },
  {
    "city": "กระบี่",
    "temp": 32.11,
    "condition": "เมฆเป็นหย่อม ๆ"
  },
  {
    "city": "กาญจนบุรี",
    "temp": 33.31,
    "condition": "เมฆเต็มท้องฟ้า"
  },
  {
    "city": "กาฬสินธุ์",
    "temp": 29.71,
    "condition": "เมฆเต็มท้องฟ้า"
  },
  {
    "city": "กำแพงเพชร",
    "temp": 32.07,
    "condition": "เมฆเต็มท้องฟ้า"
  },
  {
    "city": "ขอนแก่น",
    "temp": 32.17,
    "condition": "เมฆเป็นหย่อม ๆ"
  },
  {
    "city": "จันทบุรี",
    "temp": 31.86,
    "condition": "ฝนปานกลาง"
  },
  {
    "city": "ฉะเชิงเทรา",
    "temp": 33.76,
    "condition": "เมฆเต็มท้องฟ้า"
  },
  {
    "city": "ชลบุรี",
    "temp": 26.79,
    "condition": "เมฆเต็มท้องฟ้า"
  },
  {
    "city": "ชัยนาท",
    "temp": 34.95,
    "condition": "เมฆเต็มท้องฟ้า"
  },
  {
    "city": "ชัยภูมิ",
    "temp": 32.06,
    "condition": "เมฆเต็มท้องฟ้า"
  },
  {
    "city": "ชุมพร",
    "temp": 29.42,
    "condition": "เมฆเต็มท้องฟ้า"
  },
  {
    "city": "เชียงราย",
    "temp": 25.8,
    "condition": "เมฆเป็นหย่อม ๆ"
  },
  {
    "city": "เชียงใหม่",
    "temp": 27.94,
    "condition": "เมฆเป็นหย่อม ๆ"
  },
  {
    "city": "ตรัง",
    "temp": 31.95,
    "condition": "เมฆเล็กน้อย"
  },
  {
    "city": "ตราด",
    "temp": 29.18,
    "condition": "ฝนเบา ๆ"
  },
  {
    "city": "ตาก",
    "temp": 30.91,
    "condition": "เมฆเต็มท้องฟ้า"
  },
  {
    "city": "นครนายก",
    "temp": 33.26,
    "condition": "เมฆเต็มท้องฟ้า"
  },
  {
    "city": "นครปฐม",
    "temp": 31.08,
    "condition": "เมฆเต็มท้องฟ้า"
  },
  {
    "city": "นครพนม",
    "temp": 28.14,
    "condition": "เมฆเป็นหย่อม ๆ"
  },
  {
    "city": "นครราชสีมา",
    "temp": 33.26,
    "condition": "เมฆเต็มท้องฟ้า"
  },
  {
    "city": "นครศรีธรรมราช",
    "temp": 33.97,
    "condition": "เมฆเล็กน้อย"
  },
  {
    "city": "นครสวรรค์",
    "temp": 35.59,
    "condition": "เมฆเต็มท้องฟ้า"
  },
  {
    "city": "นนทบุรี",
    "temp": 32.98,
    "condition": "เมฆกระจาย"
  },
  {
    "city": "นราธิวาส",
    "temp": 32.01,
    "condition": "เมฆเล็กน้อย"
  },
  {
    "city": "น่าน",
    "temp": 27.92,
    "condition": "เมฆเป็นหย่อม ๆ"
  },
  {
    "city": "บึงกาฬ",
    "temp": 30.03,
    "condition": "ฝนเบา ๆ"
  },
  {
    "city": "บุรีรัมย์",
    "temp": 32.01,
    "condition": "เมฆเต็มท้องฟ้า"
  },
  {
    "city": "ปทุมธานี",
    "temp": 32.99,
    "condition": "เมฆกระจาย"
  },
  {
    "city": "ประจวบคีรีขันธ์",
    "temp": 30.57,
    "condition": "เมฆเต็มท้องฟ้า"
  },
  {
    "city": "ปราจีนบุรี",
    "temp": 34.01,
    "condition": "ฝนปานกลาง"
  },
  {
    "city": "ปัตตานี",
    "temp": 35.01,
    "condition": "ท้องฟ้าแจ่มใส"
  },
  {
    "city": "พระนครศรีอยุธยา",
    "temp": 34.2,
    "condition": "เมฆเต็มท้องฟ้า"
  },
  {
    "city": "พังงา",
    "temp": 29.25,
    "condition": "เมฆเต็มท้องฟ้า"
  },
  {
    "city": "พัทลุง",
    "temp": 32.6,
    "condition": "เมฆกระจาย"
  },
  {
    "city": "พิจิตร",
    "temp": 33.41,
    "condition": "เมฆเต็มท้องฟ้า"
  },
  {
    "city": "พิษณุโลก",
    "temp": 30.97,
    "condition": "เมฆเล็กน้อย"
  },
  {
    "city": "เพชรบุรี",
    "temp": 33.36,
    "condition": "เมฆเต็มท้องฟ้า"
  },
  {
    "city": "เพชรบูรณ์",
    "temp": 32.12,
    "condition": "เมฆเต็มท้องฟ้า"
  },
  {
    "city": "แพร่",
    "temp": 28.36,
    "condition": "เมฆเป็นหย่อม ๆ"
  },
  {
    "city": "ภูเก็ต",
    "temp": 31.12,
    "condition": "เมฆกระจาย"
  },
  {
    "city": "มหาสารคาม",
    "temp": 30.48,
    "condition": "เมฆเต็มท้องฟ้า"
  },
  {
    "city": "มุกดาหาร",
    "temp": 31.02,
    "condition": "เมฆเป็นหย่อม ๆ"
  },
  {
    "city": "แม่ฮ่องสอน",
    "temp": 30.08,
    "condition": "เมฆเป็นหย่อม ๆ"
  },
  {
    "city": "ยโสธร",
    "temp": 31.72,
    "condition": "เมฆเต็มท้องฟ้า"
  },
  {
    "city": "ยะลา",
    "temp": 37.83,
    "condition": "เมฆเล็กน้อย"
  },
  {
    "city": "ร้อยเอ็ด",
    "temp": 31.9,
    "condition": "เมฆกระจาย"
  },
  {
    "city": "ระนอง",
    "temp": 30.96,
    "condition": "เมฆเต็มท้องฟ้า"
  },
  {
    "city": "ระยอง",
    "temp": 30.05,
    "condition": "ฝนเบา ๆ"
  },
  {
    "city": "ราชบุรี",
    "temp": 33.85,
    "condition": "เมฆเต็มท้องฟ้า"
  },
  {
    "city": "ลพบุรี",
    "temp": 33.84,
    "condition": "เมฆเต็มท้องฟ้า"
  },
  {
    "city": "ลำปาง",
    "temp": 29.04,
    "condition": "เมฆเป็นหย่อม ๆ"
  },
  {
    "city": "ลำพูน",
    "temp": 27.21,
    "condition": "เมฆเต็มท้องฟ้า"
  },
  {
    "city": "เลย",
    "temp": 28.07,
    "condition": "เมฆเป็นหย่อม ๆ"
  },
  {
    "city": "ศรีสะเกษ",
    "temp": 32.5,
    "condition": "เมฆเต็มท้องฟ้า"
  },
  {
    "city": "สกลนคร",
    "temp": 29.97,
    "condition": "เมฆเป็นหย่อม ๆ"
  },
  {
    "city": "สงขลา",
    "temp": 32.94,
    "condition": "เมฆเล็กน้อย"
  },
  {
    "city": "สตูล",
    "temp": 31.83,
    "condition": "ท้องฟ้าแจ่มใส"
  },
  {
    "city": "สมุทรปราการ",
    "temp": 32,
    "condition": "เมฆเล็กน้อย"
  },
  {
    "city": "สมุทรสงคราม",
    "temp": 34.14,
    "condition": "เมฆเต็มท้องฟ้า"
  },
  {
    "city": "สมุทรสาคร",
    "temp": 31.09,
    "condition": "เมฆเต็มท้องฟ้า"
  },
  {
    "city": "สระแก้ว",
    "temp": 33.6,
    "condition": "เมฆเต็มท้องฟ้า"
  },
  {
    "city": "สระบุรี",
    "temp": 34.1,
    "condition": "เมฆเต็มท้องฟ้า"
  },
  {
    "city": "สิงห์บุรี",
    "temp": 34.83,
    "condition": "เมฆเต็มท้องฟ้า"
  },
  {
    "city": "สุโขทัย",
    "temp": 31.02,
    "condition": "เมฆเต็มท้องฟ้า"
  },
  {
    "city": "สุพรรณบุรี",
    "temp": 34.13,
    "condition": "เมฆเต็มท้องฟ้า"
  },
  {
    "city": "สุราษฎร์ธานี",
    "temp": 35.01,
    "condition": "เมฆเต็มท้องฟ้า"
  },
  {
    "city": "สุรินทร์",
    "temp": 31.82,
    "condition": "เมฆเต็มท้องฟ้า"
  },
  {
    "city": "หนองคาย",
    "temp": 32.01,
    "condition": "เมฆเต็มท้องฟ้า"
  },
  {
    "city": "หนองบัวลำภู",
    "temp": 29.4,
    "condition": "เมฆเต็มท้องฟ้า"
  },
  {
    "city": "อ่างทอง",
    "temp": 34.08,
    "condition": "เมฆเต็มท้องฟ้า"
  },
  {
    "city": "อำนาจเจริญ",
    "temp": 31.02,
    "condition": "เมฆเต็มท้องฟ้า"
  },
  {
    "city": "อุดรธานี",
    "temp": 32.95,
    "condition": "เมฆกระจาย"
  },
  {
    "city": "อุตรดิตถ์",
    "temp": 31.78,
    "condition": "เมฆเต็มท้องฟ้า"
  },
  {
    "city": "อุทัยธานี",
    "temp": 34.89,
    "condition": "เมฆเต็มท้องฟ้า"
  },
  {
    "city": "อุบลราชธานี",
    "temp": 30.9,
    "condition": "เมฆเต็มท้องฟ้า"
  }
]